LICENSE
MANIFEST.in
README.rst
requirements.txt
setup.py
network_dict/__init__.py
network_dict.egg-info/PKG-INFO
network_dict.egg-info/SOURCES.txt
network_dict.egg-info/dependency_links.txt
network_dict.egg-info/requires.txt
network_dict.egg-info/top_level.txt