Metadata-Version: 1.1
Name: network-dict
Version: 0.1
Summary: network_dict creates a network subnet based dictionary that returns the most specific subnet(s) for a given IP.
Home-page: https://github.com/neoCrimeLabs/python-network_dict
Author: Michael Henry a.k.a. neoCrimeLabs
Author-email: mhenry@neocri.me
License: LGPLv2.1
Platform: UNKNOWN
Classifier: Development Status :: 4 - Beta
Classifier: Intended Audience :: Developers
Classifier: License :: OSI Approved :: GNU Lesser General Public License v2 or later (LGPLv2+)
Classifier: Operating System :: OS Independent
Classifier: Programming Language :: Python :: 2
Classifier: Topic :: System :: Networking
